{
  "id": "48af3bc2-c826-41fa-848d-fe1b76150517",
  "definition": {},
  "globalSettings": {
    "appInMaintenance": false,
    "canvasMaxWidth": 100,
    "canvasMaxWidthType": "%",
    "canvasMaxHeight": 2400,
    "canvasBackgroundColor": "var(--cc-appBackground-surface)",
    "backgroundFxQuery": "",
    "appMode": "light"
  },
  "pageSettings": {},
  "showViewerNavigation": false,
  "homePageId": "837639c3-f1f0-41eb-b124-7576cb794a88",
  "versionType": "branch",
  "appId": "1c9941d2-09cd-4a66-a9a0-753370788b98",
  "promotedFrom": null,
  "status": "DRAFT",
  "description": null,
  "publishedAt": null,
  "releasedAt": null,
  "isStub": false,
  "moduleReferenceId": "6fff2f08-3c93-40cb-b668-466ea4dd13af",
  "sourceTag": null
}