{
  "id": "19bf6b7e-718d-42a5-b81d-a3af82bf9c41",
  "definition": {},
  "globalSettings": {
    "appInMaintenance": false,
    "canvasMaxWidth": 100,
    "canvasMaxWidthType": "%",
    "canvasMaxHeight": 2400,
    "canvasBackgroundColor": "var(--cc-appBackground-surface)",
    "backgroundFxQuery": "",
    "appMode": "light"
  },
  "pageSettings": {},
  "showViewerNavigation": false,
  "homePageId": "ea23cf29-e23b-4c9b-9826-3dff67dd33ba",
  "versionType": "version",
  "appId": "19bf6b7e-718d-42a5-b81d-a3af82bf9c41",
  "promotedFrom": null,
  "status": "DRAFT",
  "description": null,
  "publishedAt": null,
  "releasedAt": null,
  "isStub": false,
  "moduleReferenceId": "b0cab636-5cb8-483a-8698-9a0cae09cb3e",
  "sourceTag": null
}