{
  "id": "1ea17a12-08cf-4956-9cd2-12455429f41d",
  "name": "embeddedmodulepinned",
  "type": "ModuleViewer",
  "pageId": "659875fb-2953-4261-9166-4e2cf4bba54a",
  "parent": null,
  "properties": {
    "moduleAppId": {
      "value": "6326160d-d3ac-4167-a69b-ea1976686b3a"
    },
    "moduleVersionId": {
      "value": "c25c552f-ccd7-4e9a-8034-7b3614acef4f"
    },
    "visibility": {
      "value": true
    }
  },
  "general": null,
  "styles": {},
  "generalStyles": null,
  "displayPreferences": null,
  "validation": {},
  "layouts": [
    {
      "id": "d17f4294-0a29-4338-b4b2-21cb4e00cb77",
      "type": "desktop",
      "top": 20,
      "left": 5,
      "width": 30,
      "height": 400,
      "componentId": "1ea17a12-08cf-4956-9cd2-12455429f41d",
      "dimensionUnit": "count"
    },
    {
      "id": "d6224708-cf67-4c92-9e7c-6668f6c80a05",
      "type": "mobile",
      "top": 20,
      "left": 0,
      "width": 12,
      "height": 400,
      "componentId": "1ea17a12-08cf-4956-9cd2-12455429f41d",
      "dimensionUnit": "count"
    }
  ]
}